{
  "news": [
    {
      "id": 5,
      "title": "屏東縣政府公告：2024年路燈維修計畫開始實施",
      "summary": "為提升道路照明品質，將於4月起展開全縣路燈維修計畫...",
      "content": "為提升道路照明品質，全縣將於4月起展開路燈維修計畫，涵蓋主要道路與偏鄉地區，重點包括修復損壞路燈、更換老舊燈具及升級為節能LED燈。第一階段處理交通流量大的主幹道，並設交通疏導措施。市民可透過報修平台反映問題，整體計畫預計年底前完成，將有效提升安全與環保效益。",
      "date": "2024-03-25",
      "important": false
    },
    {
      "id": 2,
      "title": "1999服務專線系統維護通知",
      "summary": "為提供更好的服務品質，本系統將於4月1日凌晨2:00-4:00進行系統維護...",
      "content": "為提供更好的服務品質，本系統將於4月1日凌晨2:00-4:00進行系統維護，屆時部分服務將暫停。請提前安排相關作業，對此造成的不便敬請見諒，感謝您的支持與配合。",
      "date": "2024-03-23",
      "important": true
    },
    {
      "id": 3,
      "title": "便民服務新措施上線公告",
      "summary": "即日起，民眾可透過線上系統申請戶籍謄本，免除臨櫃等待時間...",
      "content": "即日起，民眾可透過線上系統申請戶籍謄本，免除臨櫃等待時間。此系統24小時運行，申請流程簡便快速，全面提升服務便利性與效率，提供更佳使用體驗，讓民眾享受高效便捷的公共服務。",
      "date": "2024-03-20",
      "important": false
    }
  ]
}
